pyparsonic/__init__.py
pyparsonic-0.0.0a1.dist-info/METADATA
pyparsonic-0.0.0a1.dist-info/WHEEL
pyparsonic-0.0.0a1.dist-info/top_level.txt
pyparsonic-0.0.0a1.dist-info/RECORD
