Metadata-Version: 2.1
Name: pyparsonic
Version: 0.0.0a1
Summary: Coming soon
Author-email: Simon Schoonjans <simon.schoonjans99@gmail.com>
